ois.py
varconv.cpython-36m-darwin.so
ois-0.1.4.dist-info/DESCRIPTION.rst
ois-0.1.4.dist-info/METADATA
ois-0.1.4.dist-info/RECORD
ois-0.1.4.dist-info/WHEEL
ois-0.1.4.dist-info/metadata.json
ois-0.1.4.dist-info/top_level.txt
